[
  {
    "id": 1,
    "name": "Portfolio Website",
    "image": "https://imgur.com/mKkz0iz.png",
    "description": "Portfolio website",
    "tags": ["React", "Node", "JavaScript", "SCSS"],
    "demo": "https://shahnawazfakir.github.io/"
  },
  {
    "id": 2,
    "name": "Weather App",
    "image": "https://imgur.com/tAZotn3.png",
    "description": "Weather app",
    "tags": ["react", "node", "html"],
    "demo": "https://shahnawazfakir.github.io/weather/"
  },
  {
    "id": 4,
    "name": "VSCode Portfolio",
    "image": "https://imgur.com/mKkz0iz.png",
    "description": "A themeable and developer-centric portfolio based on the VSCode",
    "tags": ["next", "css-modules"],
    "source_code": "https://github.com/shahnawazfakir/vscode",
    "demo": "https://shahnawazfakir.vercel.app/"
  }
]
